{
    "swagger": "2.0",
    "info": {
        "description": "This is the GopherSignal API server.",
        "title": "GopherSignal API",
        "contact": {},
        "version": "1"
    },
    "host": "gophersignal.com",
    "basePath": "/api/v1",
    "paths": {
        "/articles": {
            "get": {
                "description": "Retrieve a list of articles from the store",
                "consumes": [
                    "application/json"
                ],
                "produces": [
                    "application/json"
                ],
                "tags": [
                    "articles"
                ],
                "summary": "Get articles",
                "responses": {
                    "200": {
                        "description": "OK",
                        "schema": {
                            "type": "array",
                            "items": {
                                "allOf": [
                                    {
                                        "$ref": "#/definitions/models.Response"
                                    },
                                    {
                                        "type": "object",
                                        "properties": {
                                            "data": {
                                                "type": "array",
                                                "items": {
                                                    "$ref": "#/definitions/models.ArticleResponse"
                                                }
                                            }
                                        }
                                    }
                                ]
                            }
                        }
                    },
                    "500": {
                        "description": "Internal Server Error",
                        "schema": {
                            "allOf": [
                                {
                                    "$ref": "#/definitions/models.Response"
                                },
                                {
                                    "type": "object",
                                    "properties": {
                                        "data": {
                                            "type": "string"
                                        }
                                    }
                                }
                            ]
                        }
                    }
                }
            }
        }
    },
    "definitions": {
        "models.ArticleResponse": {
            "type": "object",
            "properties": {
                "content": {
                    "type": "string"
                },
                "id": {
                    "type": "integer"
                },
                "link": {
                    "type": "string"
                },
                "source": {
                    "type": "string"
                },
                "summary": {
                    "type": "string"
                },
                "title": {
                    "type": "string"
                }
            }
        },
        "models.Response": {
            "type": "object",
            "properties": {
                "code": {
                    "type": "integer"
                },
                "data": {},
                "status": {
                    "type": "string"
                }
            }
        }
    }
}